setup.py
k2k/__init__.py
k2k.egg-info/PKG-INFO
k2k.egg-info/SOURCES.txt
k2k.egg-info/dependency_links.txt
k2k.egg-info/not-zip-safe
k2k.egg-info/top_level.txt