Metadata-Version: 1.0
Name: k2k
Version: 2.0
Summary: merge some files according to the same value
Home-page: UNKNOWN
Author: tianguolangzi
Author-email: tianguolangzi@yahoo.com
License: MIT
Platform: UNKNOWN
